{
    "data": [
        {
            "currency": "USD",
            "buy": "4050",
            "sell": "4000"
        },
        {
            "currency": "EUR",
            "buy": "4469",
            "sell": "4371"
        },
        {
            "currency": "SGD",
            "buy": "2990",
            "sell": "2940"
        },
        {
            "currency": "MYR",
            "buy": "860",
            "sell": "841"
        },
        {
            "currency": "CNY",
            "buy": "560.00",
            "sell": "550.00"
        },
        {
            "currency": "THB",
            "buy": "111.11",
            "sell": "108.70"
        },
        {
            "currency": "JPN",
            "buy": "25.92",
            "sell": "25.36"
        }
    ],
    "epoch": 1716193051.1927993,
    "timestamp": "2024-05-20 14:47:31"
}